igc_processor/__init__.py
igc_processor/circling.py
igc_processor/parser.py
igc_processor/util.py
igc_processor-0.1.1.dist-info/LICENSE
igc_processor-0.1.1.dist-info/METADATA
igc_processor-0.1.1.dist-info/WHEEL
igc_processor-0.1.1.dist-info/RECORD
